setup.py
VGPY/__init__.py
VGPY/vango_openapi.py
VGPY.egg-info/PKG-INFO
VGPY.egg-info/SOURCES.txt
VGPY.egg-info/dependency_links.txt
VGPY.egg-info/top_level.txt