Metadata-Version: 2.1
Name: VGPY
Version: 1.0.1
Summary: van_go open api
Home-page: https://github.com/JanVee/VGPY
Author: JanVee
Author-email: 814107539@qq.com
License: MIT Licence
Keywords: vango,VGPY
Platform: any
